utils_eth/__init__.py
utils_eth/__main__.py
utils_eth/abi.py
utils_eth/address.py
utils_eth/applicators.py
utils_eth/conversions.py
utils_eth/crypto.py
utils_eth/currency.py
utils_eth/debug.py
utils_eth/decorators.py
utils_eth/encoding.py
utils_eth/exceptions.py
utils_eth/functional.py
utils_eth/hexadecimal.py
utils_eth/humanize.py
utils_eth/logging.py
utils_eth/module_loading.py
utils_eth/numeric.py
utils_eth/py.typed
utils_eth/toolz.py
utils_eth/types.py
utils_eth/units.py
utils_eth/curried/__init__.py
utils_eth/typing/__init__.py
utils_eth/typing/misc.py
utils_eth-2.0.5.dist-info/LICENSE
utils_eth-2.0.5.dist-info/METADATA
utils_eth-2.0.5.dist-info/WHEEL
utils_eth-2.0.5.dist-info/top_level.txt
utils_eth-2.0.5.dist-info/RECORD
