Metadata-Version: 2.1
Name: utils-eth
Version: 2.0.5
Summary: utils-eth: Common utility functions for python code that interacts with Ethereum
Home-page: https://github.com/ethereum/eth-utils
Author: The Ethereum Foundation
Author-email: snakecharmers@ethereum.org
License: MIT
Keywords: ethereum
Classifier: Intended Audience :: Developers
Classifier: License :: OSI Approved :: MIT License
Classifier: Natural Language :: English
Classifier: Programming Language :: Python :: 3
Classifier: Programming Language :: Python :: 3.6
Classifier: Programming Language :: Python :: 3.7
Classifier: Programming Language :: Python :: 3.8
Classifier: Programming Language :: Python :: 3.9
Classifier: Programming Language :: Python :: 3.10
Classifier: Programming Language :: Python :: Implementation :: PyPy
Requires-Python: >=3.6,<4
License-File: LICENSE
Requires-Dist: eth-hash (<0.6.0,>=0.3.1)
Requires-Dist: eth-typing (<4.0.0,>=3.0.0)
Requires-Dist: cytoolz (<1.0.0,>=0.10.1) ; implementation_name == "cpython"
Requires-Dist: toolz (<1,>0.8.2) ; implementation_name == "pypy"
Provides-Extra: dev
Requires-Dist: bumpversion (<1,>=0.5.3) ; extra == 'dev'
Requires-Dist: pytest-watch (<5,>=4.1.0) ; extra == 'dev'
Requires-Dist: wheel (<1.0.0,>=0.30.0) ; extra == 'dev'
Requires-Dist: twine (<2,>=1.13) ; extra == 'dev'
Requires-Dist: ipython ; extra == 'dev'
Requires-Dist: hypothesis (<5.0.0,>=4.43.0) ; extra == 'dev'
Requires-Dist: pytest (<7,>=6.2.5) ; extra == 'dev'
Requires-Dist: pytest-xdist ; extra == 'dev'
Requires-Dist: tox (==3.14.6) ; extra == 'dev'
Requires-Dist: types-setuptools ; extra == 'dev'
Requires-Dist: black (<19,>=18.6b4) ; extra == 'dev'
Requires-Dist: flake8 (==3.7.9) ; extra == 'dev'
Requires-Dist: isort (<5,>=4.2.15) ; extra == 'dev'
Requires-Dist: mypy (==0.910) ; extra == 'dev'
Requires-Dist: pydocstyle (<6,>=5.0.0) ; extra == 'dev'
Requires-Dist: Sphinx (<2,>=1.6.5) ; extra == 'dev'
Requires-Dist: sphinx-rtd-theme (<2,>=0.1.9) ; extra == 'dev'
Requires-Dist: towncrier (<20,>=19.2.0) ; extra == 'dev'
Provides-Extra: doc
Requires-Dist: Sphinx (<2,>=1.6.5) ; extra == 'doc'
Requires-Dist: sphinx-rtd-theme (<2,>=0.1.9) ; extra == 'doc'
Requires-Dist: towncrier (<20,>=19.2.0) ; extra == 'doc'
Provides-Extra: lint
Requires-Dist: black (<19,>=18.6b4) ; extra == 'lint'
Requires-Dist: flake8 (==3.7.9) ; extra == 'lint'
Requires-Dist: isort (<5,>=4.2.15) ; extra == 'lint'
Requires-Dist: mypy (==0.910) ; extra == 'lint'
Requires-Dist: pydocstyle (<6,>=5.0.0) ; extra == 'lint'
Requires-Dist: pytest (<7,>=6.2.5) ; extra == 'lint'
Requires-Dist: types-setuptools ; extra == 'lint'
Provides-Extra: test
Requires-Dist: hypothesis (<5.0.0,>=4.43.0) ; extra == 'test'
Requires-Dist: pytest (<7,>=6.2.5) ; extra == 'test'
Requires-Dist: pytest-xdist ; extra == 'test'
Requires-Dist: tox (==3.14.6) ; extra == 'test'
Requires-Dist: types-setuptools ; extra == 'test'
